delayedqueue/__init__.py
delayedqueue/delayed_queue_item.py
delayedqueue/delayedqueue.py
delayedqueue-1.0.0.dist-info/LICENSE.txt
delayedqueue-1.0.0.dist-info/METADATA
delayedqueue-1.0.0.dist-info/WHEEL
delayedqueue-1.0.0.dist-info/top_level.txt
delayedqueue-1.0.0.dist-info/RECORD
