Metadata-Version: 2.1
Name: delayedqueue
Version: 1.0.0
Summary: Thread safe delay queue implementation
Home-page: https://github.com/syogaraj/delayedqueue/
Author: Yogaraj.S
Author-email: yoga30696@gmail.com
License: MIT
Platform: any
Classifier: Development Status :: 5 - Production/Stable
Classifier: Programming Language :: Python
Classifier: Topic :: Utilities
Classifier: License :: OSI Approved :: MIT License
License-File: LICENSE.txt
Requires-Dist: importlib-metadata ; python_version < "3.8"
Provides-Extra: testing
Requires-Dist: setuptools ; extra == 'testing'
Requires-Dist: pytest ; extra == 'testing'
Requires-Dist: pytest-cov ; extra == 'testing'
